karrio/mappers/dpdhl/__init__.py
karrio/mappers/dpdhl/mapper.py
karrio/mappers/dpdhl/proxy.py
karrio/mappers/dpdhl/settings.py
karrio/providers/dpdhl/__init__.py
karrio/providers/dpdhl/error.py
karrio/providers/dpdhl/tracking.py
karrio/providers/dpdhl/units.py
karrio/providers/dpdhl/utils.py
karrio/providers/dpdhl/shipment/__init__.py
karrio/providers/dpdhl/shipment/cancel.py
karrio/providers/dpdhl/shipment/create.py
karrio/schemas/dpdhl/__init__.py
karrio/schemas/dpdhl/business_interface.py
karrio/schemas/dpdhl/customer_interface.py
karrio/schemas/dpdhl/tracking_request.py
karrio/schemas/dpdhl/tracking_response.py
karrio.dpdhl-2023.9.2.dist-info/METADATA
karrio.dpdhl-2023.9.2.dist-info/WHEEL
karrio.dpdhl-2023.9.2.dist-info/top_level.txt
karrio.dpdhl-2023.9.2.dist-info/RECORD
