Metadata-Version: 2.1
Name: karrio.dpdhl
Version: 2023.9.2
Summary: Karrio - Deutsche Post DHL Shipping extension
Home-page: https://github.com/karrioapi/karrio
Author: karrio
Author-email: hello@karrio.io
License: Apache-2.0
Classifier: Intended Audience :: Developers
Classifier: Operating System :: OS Independent
Classifier: Programming Language :: Python :: 3
Requires-Dist: karrio
